{"e":[3252,2461,8000,5919,2460,2463,8652,2817,2470,2462,4540,5920,817],"e c ed ceteri":[2470],"e ceteri":[1551],"e dek metri de me":[11237],"e di":[4426],"e ke":[10287],"e me tranchis mea lingro":[10636],"e pose metar oli averse":[9026],"e precipue":[8353],"e tale pluse":[10287],"eben arboro":[680],"ebenarboro":[2464],"ebeniero":[2464],"ebenisto":[2464,6542,4987],"ebenligno":[2464],"ebeno":[2464],"ebl":[2466],"ebla":[10946],"ebonito":[2465],"ebria":[2467],"ebriega":[2467],"ebriema":[2467],"ebriemeso":[2467],"ebrieso":[2467],"ebrieta":[2467],"ebriigar":[4554,2467,892],"ebuliar":[2468,1298],"ebulieso":[2468],"ebulio":[2468],"ebulioskopo":[2469],"ecelanta":[7919],"ecelar":[2471],"ecelenco":[2472],"ecelo":[2641],"ecentrika":[2473],"ecept":[2474],"ecepta":[2474,3478],"eceptajo":[2474],"eceptala":[2474,5654],"eceptale":[2474],"eceptar":[2474],"ecepte":[2474],"ecepte ke":[2474],"ecesajo":[2475],"ecesanta":[2475],"ecesar":[2475],"ecese":[2475],"ecesi blazas la gusto":[1270],"ecesiva":[2475],"eceso":[2475],"echekar":[2476],"echopo":[2477],"ecitar":[2478,10011],"ecizar":[2479],"ed":[2480,2481],"edelweiss":[2482],"edemo":[2483],"edeno":[2484],"ederduna kovrilo":[2486],"ederduno":[2486],"edero":[2485],"edifico":[2487],"edifikar":[2488],"ediktar":[2489],"edilo":[2490],"edipus":[2491],"edit":[2492],"editajo":[2492],"editanto":[2492],"editar":[2492,8844,8612],"editero":[2492],"editisto":[2492],"edituro":[2492],"edogena":[2681],"edro":[2493],"edukar":[2494,4485],"edukata":[2420],"edukerio":[2917],"edukisto":[15],"efacar":[2495,7369],"efacesar":[2495],"efacilo":[2495],"efebo":[2496],"efedrino":[2497],"efektigar":[2498],"efektigo":[2498],"efektivo":[2499],"efekto":[2498],"efekto rezultajo":[5072],"efemera":[2500],"efemera insekto":[2500],"efemerido":[2501],"efemero":[2500],"efervecar":[2502,2468],"eficienta":[2503],"efikanta":[2504],"efikar":[2504,2498],"efikema":[2504],"efikemeso":[2504],"efikeskar":[2504],"efikiva":[2504],"efikiva sen efika":[2504],"efikiveso":[2504],"efiko":[2504],"eflorecar":[2505],"efluvio":[2506],"eg":[2507],"egal":[2508],"egala":[2508],"egalema":[2508],"egalesala":[2508],"egalesar":[2508],"egaleso":[2508],"egaligar":[2508],"egarar":[2509,7916,6747,2268],"egaras":[2509],"egardar":[2510,5473],"egardar ulo kum neevitebla":[5306],"egarde":[2510],"egarde sua yuneso":[2510],"egardo":[2510],"egaresar":[2509],"egaresis":[2509],"egido":[2511],"egismo":[2512],"egista":[2512],"egisto":[2512],"eglefino":[2513],"ego":[2512],"egoismo":[370],"egorjar":[2514],"egotismo":[2515],"egotisto":[2516],"egreto":[2517],"eis":[2518],"ejakular":[2519],"ejektar":[2520],"ek":[2521,1,3052,7984,9760,2373,2884,2574,1186,1869,5703,2339,2614,4960],"ek asaltar":[789],"ek esas ocidita":[2521],"ek la katedro":[5048],"ek quo esas ta tasi li esas ek porcelano":[2521],"ek swichar":[10262],"ek vundita":[2521],"eka":[2539],"ekala":[2548],"ekanta":[2548,2524],"ekar de la patrio":[2548],"ekarte":[2523],"ekeskar":[2539],"ekeyo":[2524],"ekfluar":[2524],"ekidno":[2525],"ekigar":[2522,2529],"ekimoso":[2526],"ekino":[2527],"ekinodermo":[2528],"ekirar":[2529,2550,4595],"ekkargar":[2530],"eklampsio":[2531],"eklansar":[2532],"eklektika":[2533],"ekleziano":[2534],"eklezio":[2534,5138],"eklipsar":[2535],"eklipso lanterno":[5985],"ekliptiko":[2536],"eklogo":[2537],"ekmigrar":[2538,2726],"ekmodigar":[2539],"eko":[2522],"ekologio":[2540],"ekonom":[2541],"ekonomikala":[2543],"ekonomikisto":[2543],"ekonomiko":[2543],"ekonomio":[2542],"ekosistemo":[2544],"ekosmoso":[2545],"ekprenar":[2546],"ekpresar":[2547],"ekpulsar":[2548],"ekpulso":[3038],"ekrano":[2549],"ekreligar":[2550],"ekritar":[2551],"eksekrecar":[2552],"ekspricar":[2553],"eksuflar":[2554],"ekterigar":[2555],"ekteritoria":[2556],"ektirar":[2557,10523],"ektodermo":[2558],"ektopio":[2559],"ektoplasmo":[2560],"ektranchar":[2561],"ekube":[10852],"ekumenika":[2562],"ekvarsar":[2563],"ekvokar":[2564],"ekzemo":[2565],"el":[2566],"el amis nek l nek l":[10875],"el esas la maxim bela de la fratini":[1748],"el esas sempre friskanta per sua pedi":[3493],"el havas mikra traiti":[10617],"el mariajis su kun il malgre sua matro":[6314],"el posturas kom modelo por skultisto":[6780],"el tro amas il tro multa homi":[10763],"elaborar":[2567],"elastika":[2568,8983],"elastikajo":[2568],"elastikeso":[2568],"elastiko":[2568],"elastino":[2569],"elca":[1472],"elci":[1472],"elefantiazo":[2571],"elefanto":[2570],"elegant":[2572],"eleganta":[2572],"eleganta mondumo":[2572],"elegio":[2573],"elekt":[2574],"elektala":[2574],"elektanto":[5494,2574],"elektar":[2574,9396],"elekterala":[2574],"elekteraro":[2574],"elektero":[2574],"elektita per voci ek":[11162],"elektito":[2574],"elektiva":[2574],"elektoyuro":[2574],"elektrala":[2575],"elektrala arko":[719],"elektrala baterio":[2575],"elektrala fluo":[3341],"elektrala klosh":[2575],"elektristo":[2575],"elektrizar":[2575],"elektro":[2575],"elektrodinamiko":[2577],"elektrodo":[2576],"elektroforo":[2578],"elektrokemio":[2579],"elektrolito":[2580],"elektrolizar":[2581],"elektrologio":[2582],"elektrolumo":[2575],"elektromagnetala":[2575],"elektrometrio":[2584],"elektrometro":[2583],"elektromobilo":[2585],"elektromortigar":[2575],"elektroniko":[2587],"elektrono":[2586],"elektroskopio":[2589],"elektroskopo":[2588],"elektrostatiko":[2590],"elektrotekniko":[2591],"elektroterapio":[2592],"elektroza":[2575],"elektuario":[2593],"elementa":[2594],"elementala":[2594],"elemento":[2594],"elev":[2595],"elevaciono":[2596],"elevanta":[2595],"elevar":[2595,7,6077],"elevatoro":[2597],"elfala":[2598],"elfatra":[2598],"elfo":[2598],"eliminar":[2599],"elipso":[2600],"elipsoida":[2601],"elipsoido":[2601],"elito":[2602],"elitro":[2603],"elixiro":[2604],"elizeala agri":[2605],"elizeo":[2605],"elizionar":[2606],"elongaco":[2607],"eloquenta":[2608],"elta quan me amas ne amas me":[4614],"elti olta":[4614],"elua are used":[6222],"elua bela denti garnisas lua boko":[3640],"elua beleso remarkigis su da me":[8924],"elua dolca manieri konciliis la favoro di elua nova familio":[5387],"eludar":[2609,2987],"eludema":[2609],"eludiva":[2609],"elun":[6239],"elzevir":[2610],"em":[2611],"ema":[9918,9671,3688,10779,7783],"emaliizar":[2613],"emalio":[2613],"emalio parietoza":[2613],"emanar":[2614],"emancipar":[2615],"embalmar":[2616],"embarasar":[2617],"embargar":[2618],"embarkar":[2619],"emberizo":[2620],"emblemo":[2621],"embolio":[2623],"embolo":[2622],"embotar":[2624],"embotar kasrolo ek kupro":[2624],"embracar":[2625],"embracilo":[2625],"embragar":[2626,4431],"embrazuro":[2627],"embriogenio":[2628],"embriologio":[2629],"embriono":[2630],"embrokar":[2631,6143],"embuskar":[2632],"embuskar su":[2632],"embuskeyo":[2632],"embusko":[2632],"emendante":[2633],"emendar":[2633,5616],"emendita":[5597],"emerita":[2634],"emersar":[2635],"emetiko":[2636],"emetropa":[2637],"emfazala":[2638],"emfazar":[2638],"emfazatra":[2638],"emfazema":[2638],"emfazoza":[2638],"emfizemo":[2639],"eminenco":[2640],"eminent":[2641],"eminenta":[2641],"eminentaro":[2602,2641],"eminentega":[2641],"eminenteso":[2641],"emiro":[2642],"emisar":[2643],"emiso banko":[1041],"emo":[2612,11159,447],"emocar":[2644],"emoceskar":[2644],"emocigar":[2644],"empalar":[2645],"empatio":[2646],"emperialo":[2647],"empireo":[2648],"empirikala":[2649],"empirikismo":[2649],"empiriko":[2649],"employanto":[2650],"employar":[2650],"employato":[2650],"employero":[2650],"employisto":[2650],"employo":[7407],"employokontoro":[2650],"emposto":[2651],"emula":[2653],"emulesar":[5457],"emulsar":[2654],"emundar":[2655,10881,1351],"emuntario":[2656],"emuo":[2652],"en":[2657,11182,9760,7382,4472,8755,8183,8856,7973,2908,2471,9075,2619,3052],"en bareligar":[1060],"en bekigar":[1122],"en ca armeo":[2521],"en cenigar":[1495],"en flagranta delikto":[1837],"en gainigar":[3585],"en kazo di bezono":[1172],"en la floro di l":[3331],"en la fundo di la holdo":[3537],"en la intelektala":[6474],"en la kajo":[2657],"en la kazo ke il venoz":[5085],"en la sama rango":[8790],"en la tempi di la romani":[2155],"en la urbo":[2657],"en la vintro":[2657],"en libera aero":[6095,145],"en meza vintro":[11122],"en omna kazo":[5085],"en omna supozo":[10216],"en plektar":[8138],"en plena jorno":[4700],"en registrigar":[8877],"en swichar":[10262],"en ta loko":[8683],"en ulo":[9660,7891,4560,8183],"en urjanta kazo":[10917],"en yaro mezvalora":[11234],"enabismigar":[2658],"enanguligar":[2659],"enanto":[2701],"enar su":[11182,2723],"enar varme":[2769],"enartrabo":[2741],"enartroso":[2660],"enbareligar":[2661],"enbekigar":[2662],"enboteligar":[2663],"enbrigadigar":[2664],"enbursigar":[2665],"encefalito":[2667],"encefalo":[2666],"enceluligar":[2668],"encenigar":[2669],"enciklika":[2670],"encikliko":[2670],"enciklopedio":[2671],"encirkligar":[2672],"end":[2673],"endemika":[2675],"endemio":[2674],"endermika":[2676],"endetal":[2677],"endetala":[2677,2706],"endetale":[2677,1754],"endivio":[2678],"endodermo":[2679],"endogamio":[2680],"endokardio":[2682],"endokarpo":[2683],"endokrina":[2684],"endokrinologio":[2685],"endometrio":[2686],"endoparazito":[2687],"endoplasmo":[2688],"endorfino":[2689],"endoskopio":[2690],"endoskopo":[2690],"endospermo":[2691],"enduktar":[2692,2498,4562],"enduktar novajo":[7327],"enduktez il":[5085],"eneagono":[2693],"enemik":[2694],"enemikigar":[321],"enemiko":[423],"enemiko sur la fronto":[3504],"energetiko":[2695],"energiala":[2696],"energio":[2696],"energioza":[2696],"eneyo":[2701,2708],"enfakigar":[6198],"enfakturigar":[2697],"enfangigar":[2698],"enfilar":[2699],"enfilopaf":[2699],"enfiltrar":[2700],"enfluar":[2701],"enfokigar":[2702],"enfornigar":[2703],"engainigar":[2704],"engajar":[2705],"englutado":[3794],"engros":[2706],"engrosa":[2706,2677],"enigar":[2708],"enigmato":[2707],"enirar":[2708],"enirar furteme":[3554],"enirar la rado":[8751],"enkadrigar":[2709],"enkajigar":[2710],"enkarcerigar":[2711,2333],"enkargar":[2712],"enkasa sumo":[5010],"enkasigar":[2713],"enkaustika":[2714],"enkaustiko":[2714],"enkazernigar":[2715,5090],"enkestigar":[2716],"enkilemo":[2717],"enklitika":[2718],"enklitiko":[2718],"enklostrigar":[2719],"enkofrigar":[2720],"enkorpigar":[2721],"enlanjigar":[2722],"enlitigar":[2723],"enluminar":[2724,4315],"enmagazinigar":[2725],"enmigrar":[2726,2538],"enmixar":[2727],"eno":[2708],"enorma":[2728],"enosmoso":[2729],"enotero":[2730],"enoyar":[2731,3162],"enoyiganta":[2731],"enoyigar":[2731],"enoyiva":[2731],"enpakigar":[2732],"enposhigar":[2733],"enpotigar":[2734],"enrejistrar":[2735],"ensakigar":[2736],"ensembla movi":[2737],"ensemblo":[2737],"enskribar":[2738,9753],"enskribeyo di bagajo":[995],"enskriburo":[9753],"entablamento":[2740],"entaliar":[2741],"entamar":[2742],"enterigar":[2743,9486,10431],"enterito":[2744],"enternar":[2745],"entimemo":[2746],"ento":[2739,2866],"entomofilo":[2747],"entomologiisto":[2748],"entomologio":[2748],"entote":[2749,2737,10594],"entraprez":[2750],"entraprezajo":[2750],"entraprezar":[2750,853],"entraprezema":[2750],"entraprezisto":[2750],"entratenar":[2751],"entrateno":[2751],"entravar":[2752],"entrechato":[2754],"entremeso":[2755],"entrenar":[2756],"entrenero":[2756],"entrenisto":[2756],"entreo":[2753],"entresolo":[2757],"entronigar":[2758,10780],"entropio":[2759],"entuziasmar":[2760],"entuziasmas":[2760],"entuziasmeskar":[2760],"entuziasmo":[2760,11065,4475],"enuklear":[2761],"enumerar":[5501,2762],"enuncajo":[2763],"enuncar":[2763],"enuncar la judicio":[4707],"enuncuro":[2763],"enuro":[2738],"envarsar":[2764],"envelopar":[2765,2769,11182],"envelopilo":[2765],"enverguro":[2766],"envidiar":[2768],"envio":[2767],"envolvar":[2769,11119,2765],"enzimo":[2770],"eocena":[2771],"eoceno":[2771],"eolala harpo":[2772],"eoliana":[2773],"eolipilo":[2774],"eono":[2775],"eozino":[2776],"eozinofila":[2777],"epakto":[2778],"eparko":[2779],"eperlano":[2780],"epicena":[2781],"epicentro":[2782],"epiciklo":[2783],"epicikloido":[2784],"epidemia":[2785],"epidemiala kordono":[5613],"epidermala":[7871],"epidermo":[2786,5923],"epidermologio":[2786],"epidurala":[2787],"epifanio":[2788],"epifito":[2789],"epifizo":[2790],"epigastro":[2791],"epigenezo":[2792],"epigloto":[2793],"epigono":[2794],"epigrafio":[2796],"epigrafo":[2795],"epigramo":[2797],"epika":[2798],"epikajo":[2798],"epikala":[2798],"epikarpo":[2799],"epikatra":[2798],"epikisto":[2798],"epikurana":[2800],"epikurano":[2800],"epikurismo":[2800],"epilepsiala":[2801],"epilepsiika":[2801],"epilepsiiko":[2801],"epilepsio":[2801],"epilogo":[2802,8508],"episkopala":[2803],"episkoparo":[2803],"episkopeso":[2803],"episkopeyo":[2803],"episkopio":[2803],"episkopo":[2803],"epistemologio":[2804],"epistolala":[2805],"epistolo":[2805],"epistologismo":[2806],"epitafo":[2807],"epitalamio":[2808],"epitelio":[2809],"epiteto":[2810],"epitomigar":[2811],"epitomo":[2811],"epizodo":[2812],"epizootia":[2813],"epizootio":[2813],"epodo":[2814],"epokala":[2815],"epokifanta":[2815],"epoko":[2815],"epoleto":[2816,9581],"epruveto":[2818],"epuliso":[2819],"equaciono":[2820],"equalibrar":[7246],"equatorala teleskopo":[2821],"equatoralo":[2821],"equatoro":[2821],"equi":[2822],"equiangula":[2823],"equidistanta":[2824],"equilatera":[2825],"equilibrar":[2826],"equilibrigar":[2826],"equilibristo":[2826],"equilibro":[2826],"equilibroza":[2826],"equimultopla":[2827],"equinoxo":[2828],"equio":[2827],"equipar":[2829],"equipolar":[2830],"equipolo":[2831],"equiseto":[2832],"equitato":[2833,11254],"equitatoza":[11254],"equivalar":[2834],"er":[2835],"eratika":[2837],"erco":[2838],"erektar":[2839,10402,8903,9938],"erektas":[2839],"erektesis franda monumento":[8683],"eremito":[2840],"ergatoplasmo":[2842],"ergo":[2841],"ergotino":[2844],"ergotismo":[2845],"ergoto":[2843],"eri":[2846],"erikeyo":[2847],"eriko":[2847],"eringio":[2848],"erio":[8993,2917,7516],"eritroblasto":[2849],"eritrocito":[2850],"eritrofila":[2851],"eritrozino":[2852],"erizipelo":[2853],"erminielo":[2854],"ermino":[2854],"ermit":[2855],"ermitkrabo":[2856],"ero":[2836,6227,3082],"erodar":[2857],"erogena":[2858],"erora":[2859],"eroracho":[2859],"erorar":[2859],"erorego":[2859],"eroriganta":[2859],"erorigar":[10779,2859],"eroriva":[2859],"eroroza":[2859],"erotika":[2860],"erste":[2861],"erste hiere":[2861],"erudar":[2862],"erudesar":[2862],"erudita":[2862],"eruditeso":[2862],"erudito":[9737,2862],"eruptar":[2863],"eruptar per insulti":[2863],"eruptigar":[2863],"ervo":[2864],"es":[2865],"esamifar":[2867],"esamo":[2867],"esante":[5306],"esar":[2866,9138,5306],"esar ad":[170],"esar asertita absenta":[797],"esar balde mortonta":[6870],"esar departonta":[1869],"esar en dieto":[2203],"esar en humoro laborar":[4255],"esar heme":[4024],"esar justa":[1758,4729],"esar obstinanta pri projeto nerealigebla":[7382],"esar plantono":[8114],"esar severa":[4392],"esar skarsa":[53],"esar vertuoza pro neceseso":[11063],"esas du kloki":[5195],"esas extravaganta spensar pekunio ante recevar ol":[3069],"esas frumatine":[6447],"esas granda rabato en la preco di ca vari":[8745],"esas matino":[6964],"esas mea foyo":[3443],"esas nefacila orientizar su en la mezo di revoluciono":[7526],"esas pakto inter li":[7624],"esas proprajo di la homo":[8527],"esas quar":[6702],"esas responsanta pri la kulpi di altri":[8988],"esas temo konsiderinda":[5473],"esas un kloko":[5195],"esayo":[2868],"esbosar":[2869,1928,9732],"esbosilo":[2869],"esbosuro":[2869],"eschelono":[2870],"esenca":[11151,2871],"esencala":[2871,66],"esenco":[2871,10128],"esez prudenta":[8353],"esez yusta e ne timez":[11254],"esforcar":[2872,7885,8462],"esforco":[2872],"esforcovunduro":[2872],"eshafodala stango":[2873],"eshafodo":[2873],"eshelono":[2874],"esis ya mea kulpa":[11231],"esk":[2875],"eskadreto":[2877],"eskadro":[2877],"eskadrono":[2878],"eskalar":[2879],"eskalatoro":[2881],"eskaldar":[2880],"eskalero":[2882],"eskaleyo":[2879],"eskamotar":[2883,6275],"eskapar":[2884],"eskapema":[2884],"eskapilo":[2884],"eskapmoyeno":[2884],"eskapotubo":[2884],"eskarbilo":[1655,2886],"eskaro":[2885],"eskarolo":[2887],"eskarpa":[2888,686,40],"eskarpigar":[2888],"eskartar":[2889],"eskartar frapo":[2889],"eskartar infanto de la rivo":[2889],"eskartar la brakii":[2889],"eskartar suspekto":[2889],"eskartar ulu de la justa voyo":[2889],"eskartar velo":[2889],"eskarteso":[2889],"eskarteso di persono":[2889],"eskarto":[2889],"eskatologio":[2890],"esko":[6235,2876,8828],"eskombro":[2891],"eskopeto":[2892],"eskortesar ad ulu":[2893],"eskorto":[2893],"eskoto":[2894],"eskrokar":[2895],"eskudelo":[2896],"eskupar":[2897],"eskupilo":[2897],"esm":[2898],"esmerilio":[2899],"eso":[9138,9735,7296,9434,2866,170,63,7615,1830],"esos balde du kloki":[1013],"esotera":[2900,3026],"espad bastono":[1088],"espadagar":[2901],"espadagar pinte e tranche":[2901],"espadego":[2901],"espado":[2901],"espado bayoneto":[1103],"espado zono":[11284],"espadofisho":[2902],"espadostroko":[2901],"espadpinto":[2901],"espadzono":[2901],"espalero":[2903],"esparo":[2904],"esparseto":[2905],"espartajo":[2906],"esparto":[2906],"espartoshuo":[2906],"espelado":[7551],"espelar":[2907],"espellibro":[2907],"esperajo":[2908],"esperar":[2908],"esperema":[2908],"esperoza":[2908],"espineto":[2910],"espino":[2909],"espino blanka":[2909],"espino nigra":[2909],"esplanado":[2911],"esprese":[2912],"espreso":[2912],"esprestreno":[2912],"espritajo":[2913],"espritludo":[6227],"esprito":[2913],"espritoludo":[2913],"espritoza":[2913],"espruva":[2914],"espruvigar":[2914],"esquadano":[2915],"esquado":[2915],"establisar":[2917,10402,3367],"estad civila":[2918],"estado":[2918],"estafeto":[2919],"estakado":[2920],"estala longitudo":[2916],"estalajo":[2921],"estalar":[2921],"estalar ludkarti":[2921],"estalar mapo":[2921],"estalar robo":[2921],"estaleyo":[2921],"estampar":[2922],"estampilo":[2922],"estampuro":[2922],"estanchar":[2923],"estayo":[2924],"este":[2916],"estero":[2925],"estetiko":[2926],"estimar":[2927],"estiminda":[4372,2927],"estimindeso":[2927],"estimo":[5707,2927],"estiv":[2928],"estivar":[2928,4190],"esto":[2916,7526],"estompar":[2929],"estompilo":[2929],"estr":[2930],"estrado":[2931],"estragono":[2932],"estribo":[2933],"estriborimeno":[2933],"estribotrusilo":[2933],"estriolo":[2934],"estrogeno":[2935],"estrono":[2936],"estuario":[2937],"estublagro":[2938],"estublo":[2938],"esturjono":[10077],"esturjuno":[2939],"esvanar":[2940],"esvaninto":[2940],"et":[2941],"etajatre":[2942],"etajero":[2943],"etajo":[2942],"etalono":[2944],"etamino":[2945],"etapar":[2946],"etapeyo":[2946],"etato":[2947],"etato di spensi":[2947],"eterala":[2948],"eteratra":[2948],"eterifar":[2948],"eterigar":[2948],"eterizar":[2948],"eterna":[2949],"eterneso":[2949],"eternigar":[2949],"eterno":[2949],"etero":[2948],"eteroza":[2948],"etika":[2950],"etikala":[2950],"etikala e sociala medio":[6474],"etikala homulo":[6854],"etikaleso":[2950],"etiketizar":[2951],"etiketo":[2951],"etiko":[2950,6854,3678],"etikoza":[2950],"etikozeso":[2950],"etimologiisto":[2952],"etimologio":[2952],"etiolar":[2953],"etiologio":[2954],"etiqueto":[2955],"etmoida":[2956],"etmoido":[2956],"etno":[2957],"etnografio":[2958],"etnologiisto":[2959],"etnologio":[2959],"etologio":[2960],"etoso":[2961],"etruriana":[2962],"etuyo":[2963,3585],"etuyo di binoklo":[1213],"eudiometrio":[2965],"eudiometro":[2964],"eufemismo":[2966],"eufonio":[2967],"euforbio":[2968],"euforo":[2969],"eugeniko":[2970],"eukalipto":[2971],"eukaristio":[2972],"eunuka":[2973],"eunuko":[2973],"euro":[2974],"europa":[2975],"europaano":[2975],"europana":[2975],"europio":[2976],"eutanazio":[2977],"evaku":[2979],"evakuar":[2979],"evalu":[2980],"evaluar":[2980,5473,10354,2927,6618],"evaluar lua revenuo a franki taxar ol a franki":[1],"evaluebla":[2980],"evangeliala":[2981],"evangeliatra":[2981],"evangeliisto":[2981],"evangeliizar":[2981],"evangelio":[2981],"evangeliolibro":[2981],"evanta":[2978],"evanta yari":[2978],"evar":[2978],"eventajo":[2982,217],"eventar":[2982],"evento":[2982],"eventuala":[2983],"eventuala profiti":[2983],"eventuale":[2983],"eventualeso":[2983],"eventuali":[2983],"eventualo":[2983],"evidenta":[2984,6350],"evidenta verajo":[2984],"evidentajo":[2984],"evidenteso":[2984],"evidentinda":[2984],"evidento":[2984],"eviero":[2985],"eviktar":[2986],"evitar":[2987],"evo":[2978],"evo di raciono":[8750],"evoluciona":[2988],"evolucionala":[2988],"evolucionar":[2988],"evolucionismo":[2988],"evolucionisto":[2988],"evoluciono":[2142],"evoza":[2978],"ex":[2989],"ex segun la exemplo":[3000],"exajerar":[2990],"exakta":[2991,268,8355],"exakte":[2991],"exakteso":[2991],"exaltar":[2992,1861],"examen atesto":[868],"examenar":[2993,3041],"examenato":[2993],"exameno skribita":[2993],"examenoquestioni":[2993],"exantemo":[2994],"exarko":[2995],"exasperar":[2996],"exaucar":[2997,3852],"exegezar":[2998],"exegezo":[2998],"exekutala":[2999],"exekutantino testamentala":[2999],"exekutanto":[2999],"exekutar":[2999,8511],"exekutebla":[2999],"exekutenda":[2999],"exekutero":[2999],"exekutisto":[2999],"exempla":[3000],"exempla puniso":[3000],"exemplatra":[3000],"exemple":[3000],"exemplero":[3001],"exemplo":[3000],"exequatur":[3002],"exercar":[3003],"exercar su per halteri":[3950],"exerceyo":[3003],"exercolibro":[3003],"exergo":[3004],"exfoliar":[3005],"exhalar":[3006],"exhaustar":[3007],"exhaustar cisterno":[3007],"exhaustilo":[3007],"exhaustrobineto":[3007],"exhausttubo":[3007],"exhortar":[3008,8966,8897,8360],"exilar":[3009,7575,3065,1876,8535,8917],"exilas":[3009],"exilito":[3009],"exino":[3010],"existanta":[3011],"existanto":[3011],"existar":[3011],"exkavar":[3012,5073],"exkavilo":[3012],"exkavuro":[3012],"exkluzar":[3013],"exkluzemeso":[3013],"exkluzite":[3013],"exkluzive":[3013],"exkomunikar":[3014],"exkoriar":[3015,9750,9448],"exkorias":[9750],"exkrementi":[3016],"exkremento":[3016],"exkurs batelo":[1092],"exkursanto":[3017],"exkursar":[3017],"exkursero":[3017],"exkursobatelo":[3017],"exkuzar":[3018,7741,626],"exkuzas":[3018],"exkuzebla":[3018],"exkuzo":[3018],"exlibris":[3019],"exodo":[3020],"exogena":[3021],"exorcisar":[3022],"exordiar":[3023],"exordio":[3023],"exosfero":[3024],"exostoso":[3025],"exotera":[3026,2900],"exotika":[3027],"expansar":[3028],"expansema":[3028],"expediajo":[3029],"expedianto":[3029],"expediar":[3029],"expediar komercaji per fervoyo":[3029],"expedicionar":[3030],"expediciono":[3030],"expediero":[3029],"expediisto":[3029],"expektar":[3031,10988],"expektas":[3031],"expekteso":[3031],"expekto":[3031],"expektorar":[3032,9927],"experiencar":[3033],"experiencoza":[3033],"experimentala":[3034],"experimentar":[3034],"experta":[3035],"expertisar":[2980],"expertizar":[3036],"expertizero":[3036],"expertizisto":[3036],"expiacala":[3037],"expiacanta":[3037],"expiacar":[3037],"expirar":[3038,8986,3006,2548,827],"expirinta":[3038],"expiro":[3038],"expirodato":[3038],"explicita":[3039],"explicitigar":[3039],"explikar":[3040,4315],"explikas":[1788],"explikez quale vu facis ol":[8683],"expliko":[8750],"explorar":[3041,2993],"explot":[3042],"explotachar":[3042],"explotacho":[3042],"explotajo":[3042],"explotar":[3042],"explotebla":[3042],"exploz mashino":[6426],"explozar":[3043],"explozigar":[3043],"exploziva":[3043],"exploziva gaso":[3043],"explozivo":[3043],"exponento":[3044],"exportacajo":[3045],"exportacar":[3045,4346],"expozar":[3046,8460,6850],"expozar pikturo":[3046],"expozar sistemo":[3046],"expozeyo di la mortinti":[3046],"expozeyo di mortinti":[6870],"expozo di fotografala plako":[3046],"expozo di komercajo":[3046],"expresar":[3047],"expropriar":[3048],"extazar":[3049],"extensanto":[3050],"extensar":[3050],"extensar la lango":[5977],"extensebla":[3050],"extensivo":[3050],"extenuar":[3051],"exter":[3052],"exter la dicita decidi":[3052],"extera":[3052],"extera apliko":[3052],"exterdota":[3053],"extere":[3052],"extereso":[3052],"exterfluar":[3054],"exterjudicia":[3055],"exterklaso":[3056],"exterlanda":[3057],"exterlimita":[3058],"exterminar":[3059],"externerio":[3060],"externo":[3060],"extingar":[3061,58],"extingar debo":[3061],"extingar dursto":[3061],"extingar kandelo":[3061],"extingar la kalko":[3061],"extingo":[3061],"extirpar":[3062],"extors":[3063],"extorsajo":[3063],"extorsanto":[3063],"extorsar":[3063,8802],"extorsero":[3063],"extorsoprobo":[3063],"extra":[3064],"extra bona":[3064],"extraajo":[3064],"extradar":[3065,3009],"extradisho":[3064],"extradoso":[3066],"extraedituro":[3064],"extraktar":[3067,10523],"extraordinara":[3068,7158,7509],"extraspenso":[3064],"extravagar":[3069,2290],"extravagemeso di konduto":[3069],"extravago":[3069],"extrema":[3070,10195],"extrema frontiero":[3070],"extrema plezuro":[3070],"extrema unciono":[3070,10880],"extremajo":[3070],"extreme":[3070],"extrinseka":[3071,4561],"exudar":[3072,10663],"exultar":[3073],"exutorio":[3074],"ey":[3075],"eyo":[8993,10946],"ez":[3076],"ezofago":[3077]}