{"jab":[9801],"jabber":[9802],"jabot":[9803],"jacinth":[9804],"jack":[9805],"jackal":[9806],"jackanapes":[9807],"jackass":[9808],"jackboot":[9809],"jackdaw":[9810],"jacket":[9811,3966],"jacknife":[9812],"jackstraw":[9813],"jacobin":[9814],"jaconet":[9815],"jacquet":[9832],"jade":[9816],"jaded":[9817],"jagged":[9818],"jaguar":[9819],"jail":[9820],"jailer":[9820],"jalousie":[9821],"jam":[9823,9822],"jamb":[9824],"jangle":[9825],"jangling":[9826],"janitor":[9827],"janizary":[9828],"jansen":[9829],"january":[9830],"japan":[9831],"jar":[9834,9833],"jardiniere":[9835],"jargon":[9836],"jasmine":[9837],"jasmine perfume":[9837],"jasper":[9838],"jaundice":[9839],"jaunt":[9840],"jaunting":[9841],"jaunty":[9842],"javelin":[9843],"jaw":[9844],"jay":[9845],"jealous":[9846],"jeer":[9847],"jejune":[9848],"jelly":[9849,9850],"jeopardize":[9851],"jeopardy":[9852],"jeremiad":[9853],"jerk":[9854],"jerkin":[9855],"jerry":[9856],"jersey":[9857],"jerusalem artichoke":[9858,952],"jessamine":[9859],"jest":[9860],"jesuit":[9861],"jesus christ":[9862],"jet":[9863],"jet of water":[9863],"jetsam":[9864],"jettison":[9865],"jetty":[9866],"jew":[9867],"jewel":[9868,1988],"jig":[9869],"jigger":[9870],"jilt":[9871],"jimsonweed":[9872],"jingle":[9873],"jingo":[9874],"jinni":[9875],"job":[9876],"jobber":[9877],"jobbery":[9878],"jockey":[9879],"jockey cap":[2461],"jocular":[9880],"jocund":[9881],"jog":[9882,9896],"jog the memory":[9882],"jog trot":[9882],"join":[9883],"joiner":[9884],"joint":[9886,9888,9885],"joint account":[106],"joint signature":[16165],"joint stock":[9886],"joint stock bank":[1331],"joint stock company":[9886],"jointly":[9887],"jointure":[9889],"joist":[9890],"joke":[9891],"jollification":[9892],"jollity":[9893],"jolly":[9894,9895],"jolt":[9896],"jonquil":[9897],"jostle":[9898],"jot":[9899],"jot down":[9899],"journal":[9900],"journey":[9901],"joust":[9902],"jovial":[9903],"jowl":[9904],"joy":[9905],"jube":[9906],"jubilant":[9907],"jubilate":[9908],"jubilee":[9909],"judaic":[9910],"judaism":[9911],"judge":[9912,9913],"judgement":[9914],"judgement of god":[9914],"judicature":[9915],"judicial":[9916],"judicious":[9917],"jug":[9918],"jugged hare":[8199],"juggle":[9919],"jugular":[9920],"juice":[9921],"jujube":[9922],"julep":[9923],"julienne":[9924],"july":[9925],"jumble":[9926,9927],"jump":[9928],"junction":[9929],"june":[9930],"jungle":[9931],"junior":[9932],"juniper":[9933],"junk":[9934],"junketing":[9935],"jurassic":[9936],"juridical":[9937],"jurisconsult":[9938],"jurisdiction":[9939],"jurisprudence":[9940],"jurist":[9941],"juror":[9942],"jury":[9943],"just":[9944],"just as":[9944],"just as you say":[15490],"just at present":[9944],"just at that time":[9944],"just so":[9944],"just then":[9944],"justice":[9945],"justiceable":[9946],"justifiable":[9947],"justification":[9948],"justify":[9949],"justly":[9950],"jut out":[9951],"jute":[9952],"juvenile":[9953],"juxtapose":[9954],"juxtaposition":[9955]}